uyenobf/__init__.py
uyenobf/__main__.py
uyenobf/logger.py
uyenobf/transformers/ControlFlowTransformer.py
uyenobf/transformers/IfStatementTransformer.py
uyenobf/transformers/InOutlineTransformer.py
uyenobf/transformers/MBAExprTransformer.py
uyenobf/transformers/MemoryTransformer.py
uyenobf/transformers/OpaqueTransformer.py
uyenobf/transformers/RenamerTransformer.py
uyenobf/transformers/StringTransformer.py
uyenobf/transformers/TryCatchTransformer.py
uyenobf/transformers/TryNormalizerTransformer.py
uyenobf/transformers/__init__.py
uyenobf-0.1.0.dist-info/METADATA
uyenobf-0.1.0.dist-info/WHEEL
uyenobf-0.1.0.dist-info/RECORD
